{"generated_at":1784685938,"hotspots":[{"state":"CA","intensity":1,"basis":"317,559 FCC phone complaints, 0 vetted report(s)"},{"state":"TX","intensity":0.648,"basis":"205,657 FCC phone complaints, 0 vetted report(s)"},{"state":"FL","intensity":0.602,"basis":"191,029 FCC phone complaints, 0 vetted report(s)"},{"state":"NY","intensity":0.478,"basis":"151,899 FCC phone complaints, 0 vetted report(s)"},{"state":"PA","intensity":0.318,"basis":"101,111 FCC phone complaints, 0 vetted report(s)"},{"state":"IL","intensity":0.295,"basis":"93,656 FCC phone complaints, 0 vetted report(s)"},{"state":"OH","intensity":0.282,"basis":"89,533 FCC phone complaints, 0 vetted report(s)"},{"state":"NC","intensity":0.265,"basis":"84,038 FCC phone complaints, 0 vetted report(s)"},{"state":"GA","intensity":0.263,"basis":"83,415 FCC phone complaints, 0 vetted report(s)"},{"state":"VA","intensity":0.252,"basis":"80,045 FCC phone complaints, 0 vetted report(s)"}]}